Workbook

Sheet 原始数据
A1: 2025年度智能手表销售报表
A2: 报表日期：2026年10月10日 制表单位：星辰科技有限公司
A3: 月份 | B3: 产品型号 | C3: 销售数量(只) | D3: 单价(元) | E3: 销售金额(元) | F3: 成本(元) | G3: 利润(元)
A4: 2025年1月 | B4: StarWatch Pro | C4: 407 | D4: 1999 | E4: 813593 | F4: 447700 | G4: 365893
A5: 2025年1月 | B5: StarWatch Lite | C5: 137 | D5: 699 | E5: 95763 | F5: 52060 | G5: 43703
A6: 2025年1月 | B6: StarWatch SE | C6: 92 | D6: 999 | E6: 91908 | F6: 50600 | G6: 41308
A7: 2025年1月 | B7: StarWatch Ultra | C7: 459 | D7: 2999 | E7: 1376541 | F7: 826200 | G7: 550341
A8: 2025年2月 | B8: StarWatch Pro | C8: 220 | D8: 1999 | E8: 439780 | F8: 242000 | G8: 197780
A9: 2025年2月 | B9: StarWatch Lite | C9: 205 | D9: 699 | E9: 143295 | F9: 77900 | G9: 65395
A10: 2025年2月 | B10: StarWatch SE | C10: 194 | D10: 999 | E10: 193806 | F10: 106700 | G10: 87106
A11: 2025年2月 | B11: StarWatch Ultra | C11: 151 | D11: 2999 | E11: 452849 | F11: 271800 | G11: 181049
A12: 2025年3月 | B12: StarWatch Pro | C12: 457 | D12: 1999 | E12: 913543 | F12: 502700 | G12: 410843
A13: 2025年3月 | B13: StarWatch Lite | C13: 132 | D13: 699 | E13: 92268 | F13: 50160 | G13: 42108
A14: 2025年3月 | B14: StarWatch SE | C14: 426 | D14: 999 | E14: 425574 | F14: 234300 | G14: 191274
A15: 2025年3月 | B15: StarWatch Ultra | C15: 459 | D15: 2999 | E15: 1376541 | F15: 826200 | G15: 550341
... A51: 2025年12月 | B51: StarWatch Ultra | C51: 252 | D51: 2999 | E51: 755748 | F51: 453600 | G51: 302148
A52: 合 计 | C52: =SUM(销售明细!C4:C51) -> 13607 | E52: =SUM(销售明细!E4:E51) -> 23017593 | F52: =SUM(销售明细!F4:F51) -> 13159930 | G52: =SUM(销售明细!G4:G51) -> 9857663
G54: 内容由 AI 生成

Sheet 同产品型号合并汇总
A1: 同一产品型号数据合并汇总
A2: 序号 | B2: 产品型号 | C2: 月份 | D2: 销售数量(只) | E2: 销售金额(元) | F2: 成本(元) | G2: 利润(元)
A3: =ROW()-2 -> 1 | B3: StarWatch Lite | C3: 2025年1月、2025年2月、2025年3月、2025年4月、2025年5月、2025年6月、2025年7月、2025年8月、2025年9月、2025年10月、2025年11月、2025年12月 | D3: =SUMIFS(原始数据!$C$4:$C$51,原始数据!$B$4:$B$51,"StarWatch Lite") -> 2906 | E3: =SUMIFS(原始数据!$E$4:$E$51,原始数据!$B$4:$B$51,"StarWatch Lite") -> 2031294 | F3: =SUMIFS(原始数据!$F$4:$F$51,原始数据!$B$4:$B$51,"StarWatch Lite") -> 1104280 | G3: =SUMIFS(原始数据!$G$4:$G$51,原始数据!$B$4:$B$51,"StarWatch Lite") -> 927014
A4: =ROW()-2 -> 2 | B4: StarWatch Pro | C4: 2025年1月、2025年2月、2025年3月、2025年4月、2025年5月、2025年6月、2025年7月、2025年8月、2025年9月、2025年10月、2025年11月、2025年12月 | D4: =SUMIFS(原始数据!$C$4:$C$51,原始数据!$B$4:$B$51,"StarWatch Pro") -> 3532 | E4: =SUMIFS(原始数据!$E$4:$E$51,原始数据!$B$4:$B$51,"StarWatch Pro") -> 7060468 | F4: =SUMIFS(原始数据!$F$4:$F$51,原始数据!$B$4:$B$51,"StarWatch Pro") -> 3885200 | G4: =SUMIFS(原始数据!$G$4:$G$51,原始数据!$B$4:$B$51,"StarWatch Pro") -> 3175268
A5: =ROW()-2 -> 3 | B5: StarWatch SE | C5: 2025年1月、2025年2月、2025年3月、2025年4月、2025年5月、2025年6月、2025年7月、2025年8月、2025年9月、2025年10月、2025年11月、2025年12月 | D5: =SUMIFS(原始数据!$C$4:$C$51,原始数据!$B$4:$B$51,"StarWatch SE") -> 3787 | E5: =SUMIFS(原始数据!$E$4:$E$51,原始数据!$B$4:$B$51,"StarWatch SE") -> 3783213 | F5: =SUMIFS(原始数据!$F$4:$F$51,原始数据!$B$4:$B$51,"StarWatch SE") -> 2082850 | G5: =SUMIFS(原始数据!$G$4:$G$51,原始数据!$B$4:$B$51,"StarWatch SE") -> 1700363
A6: =ROW()-2 -> 4 | B6: StarWatch Ultra | C6: 2025年1月、2025年2月、2025年3月、2025年4月、2025年5月、2025年6月、2025年7月、2025年8月、2025年9月、2025年10月、2025年11月、2025年12月 | D6: =SUMIFS(原始数据!$C$4:$C$51,原始数据!$B$4:$B$51,"StarWatch Ultra") -> 3382 | E6: =SUMIFS(原始数据!$E$4:$E$51,原始数据!$B$4:$B$51,"StarWatch Ultra") -> 10142618 | F6: =SUMIFS(原始数据!$F$4:$F$51,原始数据!$B$4:$B$51,"StarWatch Ultra") -> 6087600 | G6: =SUMIFS(原始数据!$G$4:$G$51,原始数据!$B$4:$B$51,"StarWatch Ultra") -> 4055018

Sheet 月份利润汇总
A1: 月份利润汇总
A2: 序号 | B2: 月份 | C2: 利润(元) | D2: 涉及数据笔数 | E2: 占比
A3: =ROW()-2 -> 1 | B3: 2025年3月 | C3: =SUMIFS(原始数据!$G$4:$G$51,原始数据!$A$4:$A$51,"2025年3月") -> 1194566 | D3: =COUNTIFS(原始数据!$A$4:$A$51,"2025年3月") -> 4 | E3: =IF((SUM(原始数据!$E$4:$E$51)-SUM(原始数据!$F$4:$F$51))=0,"",C3/(SUM(原始数据!$E$4:$E$51)-SUM(原始数据!$F$4:$F$51))) -> 0.12118146
A4: =ROW()-2 -> 2 | B4: 2025年9月 | C4: =SUMIFS(原始数据!$G$4:$G$51,原始数据!$A$4:$A$51,"2025年9月") -> 1091314 | D4: =COUNTIFS(原始数据!$A$4:$A$51,"2025年9月") -> 4 | E4: =IF((SUM(原始数据!$E$4:$E$51)-SUM(原始数据!$F$4:$F$51))=0,"",C4/(SUM(原始数据!$E$4:$E$51)-SUM(原始数据!$F$4:$F$51))) -> 0.11070717
A5: =ROW()-2 -> 3 | B5: 2025年7月 | C5: =SUMIFS(原始数据!$G$4:$G$51,原始数据!$A$4:$A$51,"2025年7月") -> 1081914 | D5: =COUNTIFS(原始数据!$A$4:$A$51,"2025年7月") -> 4 | E5: =IF((SUM(原始数据!$E$4:$E$51)-SUM(原始数据!$F$4:$F$51))=0,"",C5/(SUM(原始数据!$E$4:$E$51)-SUM(原始数据!$F$4:$F$51))) -> 0.1097536
A6: =ROW()-2 -> 4 | B6: 2025年1月 | C6: =SUMIFS(原始数据!$G$4:$G$51,原始数据!$A$4:$A$51,"2025年1月") -> 1001245 | D6: =COUNTIFS(原始数据!$A$4:$A$51,"2025年1月") -> 4 | E6: =IF((SUM(原始数据!$E$4:$E$51)-SUM(原始数据!$F$4:$F$51))=0,"",C6/(SUM(原始数据!$E$4:$E$51)-SUM(原始数据!$F$4:$F$51))) -> 0.10157022
A7: =ROW()-2 -> 5 | B7: 2025年4月 | C7: =SUMIFS(原始数据!$G$4:$G$51,原始数据!$A$4:$A$51,"2025年4月") -> 888719 | D7: =COUNTIFS(原始数据!$A$4:$A$51,"2025年4月") -> 4 | E7: =IF((SUM(原始数据!$E$4:$E$51)-SUM(原始数据!$F$4:$F$51))=0,"",C7/(SUM(原始数据!$E$4:$E$51)-SUM(原始数据!$F$4:$F$51))) -> 0.090155141
A8: =ROW()-2 -> 6 | B8: 2025年8月 | C8: =SUMIFS(原始数据!$G$4:$G$51,原始数据!$A$4:$A$51,"2025年8月") -> 871396 | D8: =COUNTIFS(原始数据!$A$4:$A$51,"2025年8月") -> 4 | E8: =IF((SUM(原始数据!$E$4:$E$51)-SUM(原始数据!$F$4:$F$51))=0,"",C8/(SUM(原始数据!$E$4:$E$51)-SUM(原始数据!$F$4:$F$51))) -> 0.088397828
A9: =ROW()-2 -> 7 | B9: 2025年11月 | C9: =SUMIFS(原始数据!$G$4:$G$51,原始数据!$A$4:$A$51,"2025年11月") -> 867511 | D9: =COUNTIFS(原始数据!$A$4:$A$51,"2025年11月") -> 4 | E9: =IF((SUM(原始数据!$E$4:$E$51)-SUM(原始数据!$F$4:$F$51))=0,"",C9/(SUM(原始数据!$E$4:$E$51)-SUM(原始数据!$F$4:$F$51))) -> 0.088003719
A10: =ROW()-2 -> 8 | B10: 2025年12月 | C10: =SUMIFS(原始数据!$G$4:$G$51,原始数据!$A$4:$A$51,"2025年12月") -> 716729 | D10: =COUNTIFS(原始数据!$A$4:$A$51,"2025年12月") -> 4 | E10: =IF((SUM(原始数据!$E$4:$E$51)-SUM(原始数据!$F$4:$F$51))=0,"",C10/(SUM(原始数据!$E$4:$E$51)-SUM(原始数据!$F$4:$F$51))) -> 0.072707801
A11: =ROW()-2 -> 9 | B11: 2025年10月 | C11: =SUMIFS(原始数据!$G$4:$G$51,原始数据!$A$4:$A$51,"2025年10月") -> 637856 | D11: =COUNTIFS(原始数据!$A$4:$A$51,"2025年10月") -> 4 | E11: =IF((SUM(原始数据!$E$4:$E$51)-SUM(原始数据!$F$4:$F$51))=0,"",C11/(SUM(原始数据!$E$4:$E$51)-SUM(原始数据!$F$4:$F$51))) -> 0.064706615
A12: =ROW()-2 -> 10 | B12: 2025年6月 | C12: =SUMIFS(原始数据!$G$4:$G$51,原始数据!$A$4:$A$51,"2025年6月") -> 572442 | D12: =COUNTIFS(原始数据!$A$4:$A$51,"2025年6月") -> 4 | E12: =IF((SUM(原始数据!$E$4:$E$51)-SUM(原始数据!$F$4:$F$51))=0,"",C12/(SUM(原始数据!$E$4:$E$51)-SUM(原始数据!$F$4:$F$51))) -> 0.058070762
A13: =ROW()-2 -> 11 | B13: 2025年2月 | C13: =SUMIFS(原始数据!$G$4:$G$51,原始数据!$A$4:$A$51,"2025年2月") -> 531330 | D13: =COUNTIFS(原始数据!$A$4:$A$51,"2025年2月") -> 4 | E13: =IF((SUM(原始数据!$E$4:$E$51)-SUM(原始数据!$F$4:$F$51))=0,"",C13/(SUM(原始数据!$E$4:$E$51)-SUM(原始数据!$F$4:$F$51))) -> 0.053900199
A14: =ROW()-2 -> 12 | B14: 2025年5月 | C14: =SUMIFS(原始数据!$G$4:$G$51,原始数据!$A$4:$A$51,"2025年5月") -> 402641 | D14: =COUNTIFS(原始数据!$A$4:$A$51,"2025年5月") -> 4 | E14: =IF((SUM(原始数据!$E$4:$E$51)-SUM(原始数据!$F$4:$F$51))=0,"",C14/(SUM(原始数据!$E$4:$E$51)-SUM(原始数据!$F$4:$F$51))) -> 0.040845482

Sheet 统计总览
A1: 数据统计总览
A2: 指标 | B2: 数值
A3: 总销售数量（只） | B3: =SUM(原始数据!$C$4:$C$51) -> 13607
A4: 总销售金额（元） | B4: =SUM(原始数据!$E$4:$E$51) -> 23017593
A5: 总成本（元） | B5: =SUM(原始数据!$F$4:$F$51) -> 13159930
A6: 总利润（元） | B6: =SUM(原始数据!$G$4:$G$51) -> 9857663
A7: 整体利润率 | B7: =IF(B4=0,"",B6/B4) -> 0.42826646
A8: 总机型数 | B8: =SUMPRODUCT(1/COUNTIF(原始数据!$B$4:$B$51,原始数据!$B$4:$B$51&"")) -> 4
A9: 总数据笔数 | B9: =COUNTA(原始数据!$B$4:$B$51) -> 48

Sheet 月份统计
A1: 月份维度统计分析
A2: 序号 | B2: 月份 | C2: 总销售数量 | D2: 总销售金额 | E2: 总成本 | F2: 总利润 | G2: 机型数 | H2: 利润率 | I2: 销售额占比
A3: =ROW()-2 -> 1 | B3: 2025年3月 | C3: =SUMIFS(原始数据!$C$4:$C$51,原始数据!$A$4:$A$51,"2025年3月") -> 1474 | D3: =SUMIFS(原始数据!$E$4:$E$51,原始数据!$A$4:$A$51,"2025年3月") -> 2807926 | E3: =SUMIFS(原始数据!$F$4:$F$51,原始数据!$A$4:$A$51,"2025年3月") -> 1613360 | F3: =SUMIFS(原始数据!$G$4:$G$51,原始数据!$A$4:$A$51,"2025年3月") -> 1194566 | G3: =SUMPRODUCT((原始数据!$A$4:$A$51="2025年3月")/COUNTIFS(原始数据!$B$4:$B$51,原始数据!$B$4:$B$51&"",原始数据!$A$4:$A$51,原始数据!$A$4:$A$51&"")) -> 4 | H3: =IF(D3=0,"",F3/D3) -> 0.42542645 | I3: =IF(SUM(原始数据!$E$4:$E$51)=0,"",D3/SUM(原始数据!$E$4:$E$51)) -> 0.12199043
A4: =ROW()-2 -> 2 | B4: 2025年9月 | C4: =SUMIFS(原始数据!$C$4:$C$51,原始数据!$A$4:$A$51,"2025年9月") -> 1406 | D4: =SUMIFS(原始数据!$E$4:$E$51,原始数据!$A$4:$A$51,"2025年9月") -> 2587294 | E4: =SUMIFS(原始数据!$F$4:$F$51,原始数据!$A$4:$A$51,"2025年9月") -> 1495980 | F4: =SUMIFS(原始数据!$G$4:$G$51,原始数据!$A$4:$A$51,"2025年9月") -> 1091314 | G4: =SUMPRODUCT((原始数据!$A$4:$A$51="2025年9月")/COUNTIFS(原始数据!$B$4:$B$51,原始数据!$B$4:$B$51&"",原始数据!$A$4:$A$51,原始数据!$A$4:$A$51&"")) -> 4 | H4: =IF(D4=0,"",F4/D4) -> 0.42179745 | I4: =IF(SUM(原始数据!$E$4:$E$51)=0,"",D4/SUM(原始数据!$E$4:$E$51)) -> 0.11240506
A5: =ROW()-2 -> 3 | B5: 2025年7月 | C5: =SUMIFS(原始数据!$C$4:$C$51,原始数据!$A$4:$A$51,"2025年7月") -> 1406 | D5: =SUMIFS(原始数据!$E$4:$E$51,原始数据!$A$4:$A$51,"2025年7月") -> 2541294 | E5: =SUMIFS(原始数据!$F$4:$F$51,原始数据!$A$4:$A$51,"2025年7月") -> 1459380 | F5: =SUMIFS(原始数据!$G$4:$G$51,原始数据!$A$4:$A$51,"2025年7月") -> 1081914 | G5: =SUMPRODUCT((原始数据!$A$4:$A$51="2025年7月")/COUNTIFS(原始数据!$B$4:$B$51,原始数据!$B$4:$B$51&"",原始数据!$A$4:$A$51,原始数据!$A$4:$A$51&"")) -> 4 | H5: =IF(D5=0,"",F5/D5) -> 0.4257335 | I5: =IF(SUM(原始数据!$E$4:$E$51)=0,"",D5/SUM(原始数据!$E$4:$E$51)) -> 0.11040659
A6: =ROW()-2 -> 4 | B6: 2025年1月 | C6: =SUMIFS(原始数据!$C$4:$C$51,原始数据!$A$4:$A$51,"2025年1月") -> 1095 | D6: =SUMIFS(原始数据!$E$4:$E$51,原始数据!$A$4:$A$51,"2025年1月") -> 2377805 | E6: =SUMIFS(原始数据!$F$4:$F$51,原始数据!$A$4:$A$51,"2025年1月") -> 1376560 | F6: =SUMIFS(原始数据!$G$4:$G$51,原始数据!$A$4:$A$51,"2025年1月") -> 1001245 | G6: =SUMPRODUCT((原始数据!$A$4:$A$51="2025年1月")/COUNTIFS(原始数据!$B$4:$B$51,原始数据!$B$4:$B$51&"",原始数据!$A$4:$A$51,原始数据!$A$4:$A$51&"")) -> 4 | H6: =IF(D6=0,"",F6/D6) -> 0.42107953 | I6: =IF(SUM(原始数据!$E$4:$E$51)=0,"",D6/SUM(原始数据!$E$4:$E$51)) -> 0.10330381
A7: =ROW()-2 -> 5 | B7: 2025年4月 | C7: =SUMIFS(原始数据!$C$4:$C$51,原始数据!$A$4:$A$51,"2025年4月") -> 1161 | D7: =SUMIFS(原始数据!$E$4:$E$51,原始数据!$A$4:$A$51,"2025年4月") -> 2073639 | E7: =SUMIFS(原始数据!$F$4:$F$51,原始数据!$A$4:$A$51,"2025年4月") -> 1184920 | F7: =SUMIFS(原始数据!$G$4:$G$51,原始数据!$A$4:$A$51,"2025年4月") -> 888719 | G7: =SUMPRODUCT((原始数据!$A$4:$A$51="2025年4月")/COUNTIFS(原始数据!$B$4:$B$51,原始数据!$B$4:$B$51&"",原始数据!$A$4:$A$51,原始数据!$A$4:$A$51&"")) -> 4 | H7: =IF(D7=0,"",F7/D7) -> 0.42857942 | I7: =IF(SUM(原始数据!$E$4:$E$51)=0,"",D7/SUM(原始数据!$E$4:$E$51)) -> 0.090089307
A8: =ROW()-2 -> 6 | B8: 2025年11月 | C8: =SUMIFS(原始数据!$C$4:$C$51,原始数据!$A$4:$A$51,"2025年11月") -> 1209 | D8: =SUMIFS(原始数据!$E$4:$E$51,原始数据!$A$4:$A$51,"2025年11月") -> 1999991 | E8: =SUMIFS(原始数据!$F$4:$F$51,原始数据!$A$4:$A$51,"2025年11月") -> 1132480 | F8: =SUMIFS(原始数据!$G$4:$G$51,原始数据!$A$4:$A$51,"2025年11月") -> 867511 | G8: =SUMPRODUCT((原始数据!$A$4:$A$51="2025年11月")/COUNTIFS(原始数据!$B$4:$B$51,原始数据!$B$4:$B$51&"",原始数据!$A$4:$A$51,原始数据!$A$4:$A$51&"")) -> 4 | H8: =IF(D8=0,"",F8/D8) -> 0.43375745 | I8: =IF(SUM(原始数据!$E$4:$E$51)=0,"",D8/SUM(原始数据!$E$4:$E$51)) -> 0.086889667
A9: =ROW()-2 -> 7 | B9: 2025年8月 | C9: =SUMIFS(原始数据!$C$4:$C$51,原始数据!$A$4:$A$51,"2025年8月") -> 1284 | D9: =SUMIFS(原始数据!$E$4:$E$51,原始数据!$A$4:$A$51,"2025年8月") -> 1998016 | E9: =SUMIFS(原始数据!$F$4:$F$51,原始数据!$A$4:$A$51,"2025年8月") -> 1126620 | F9: =SUMIFS(原始数据!$G$4:$G$51,原始数据!$A$4:$A$51,"2025年8月") -> 871396 | G9: =SUMPRODUCT((原始数据!$A$4:$A$51="2025年8月")/COUNTIFS(原始数据!$B$4:$B$51,原始数据!$B$4:$B$51&"",原始数据!$A$4:$A$51,原始数据!$A$4:$A$51&"")) -> 4 | H9: =IF(D9=0,"",F9/D9) -> 0.43613064 | I9: =IF(SUM(原始数据!$E$4:$E$51)=0,"",D9/SUM(原始数据!$E$4:$E$51)) -> 0.086803863
A10: =ROW()-2 -> 8 | B10: 2025年12月 | C10: =SUMIFS(原始数据!$C$4:$C$51,原始数据!$A$4:$A$51,"2025年12月") -> 1071 | D10: =SUMIFS(原始数据!$E$4:$E$51,原始数据!$A$4:$A$51,"2025年12月") -> 1675929 | E10: =SUMIFS(原始数据!$F$4:$F$51,原始数据!$A$4:$A$51,"2025年12月") -> 959200 | F10: =SUMIFS(原始数据!$G$4:$G$51,原始数据!$A$4:$A$51,"2025年12月") -> 716729 | G10: =SUMPRODUCT((原始数据!$A$4:$A$51="2025年12月")/COUNTIFS(原始数据!$B$4:$B$51,原始数据!$B$4:$B$51&"",原始数据!$A$4:$A$51,原始数据!$A$4:$A$51&"")) -> 4 | H10: =IF(D10=0,"",F10/D10) -> 0.42766072 | I10: =IF(SUM(原始数据!$E$4:$E$51)=0,"",D10/SUM(原始数据!$E$4:$E$51)) -> 0.072810784
A11: =ROW()-2 -> 9 | B11: 2025年10月 | C11: =SUMIFS(原始数据!$C$4:$C$51,原始数据!$A$4:$A$51,"2025年10月") -> 1204 | D11: =SUMIFS(原始数据!$E$4:$E$51,原始数据!$A$4:$A$51,"2025年10月") -> 1467396 | E11: =SUMIFS(原始数据!$F$4:$F$51,原始数据!$A$4:$A$51,"2025年10月") -> 829540 | F11: =SUMIFS(原始数据!$G$4:$G$51,原始数据!$A$4:$A$51,"2025年10月") -> 637856 | G11: =SUMPRODUCT((原始数据!$A$4:$A$51="2025年10月")/COUNTIFS(原始数据!$B$4:$B$51,原始数据!$B$4:$B$51&"",原始数据!$A$4:$A$51,原始数据!$A$4:$A$51&"")) -> 4 | H11: =IF(D11=0,"",F11/D11) -> 0.43468566 | I11: =IF(SUM(原始数据!$E$4:$E$51)=0,"",D11/SUM(原始数据!$E$4:$E$51)) -> 0.063751062
A12: =ROW()-2 -> 10 | B12: 2025年6月 | C12: =SUMIFS(原始数据!$C$4:$C$51,原始数据!$A$4:$A$51,"2025年6月") -> 1018 | D12: =SUMIFS(原始数据!$E$4:$E$51,原始数据!$A$4:$A$51,"2025年6月") -> 1300582 | E12: =SUMIFS(原始数据!$F$4:$F$51,原始数据!$A$4:$A$51,"2025年6月") -> 728140 | F12: =SUMIFS(原始数据!$G$4:$G$51,原始数据!$A$4:$A$51,"2025年6月") -> 572442 | G12: =SUMPRODUCT((原始数据!$A$4:$A$51="2025年6月")/COUNTIFS(原始数据!$B$4:$B$51,原始数据!$B$4:$B$51&"",原始数据!$A$4:$A$51,原始数据!$A$4:$A$51&"")) -> 4 | H12: =IF(D12=0,"",F12/D12) -> 0.44014295 | I12: =IF(SUM(原始数据!$E$4:$E$51)=0,"",D12/SUM(原始数据!$E$4:$E$51)) -> 0.056503823
A13: =ROW()-2 -> 11 | B13: 2025年2月 | C13: =SUMIFS(原始数据!$C$4:$C$51,原始数据!$A$4:$A$51,"2025年2月") -> 770 | D13: =SUMIFS(原始数据!$E$4:$E$51,原始数据!$A$4:$A$51,"2025年2月") -> 1229730 | E13: =SUMIFS(原始数据!$F$4:$F$51,原始数据!$A$4:$A$51,"2025年2月") -> 698400 | F13: =SUMIFS(原始数据!$G$4:$G$51,原始数据!$A$4:$A$51,"2025年2月") -> 531330 | G13: =SUMPRODUCT((原始数据!$A$4:$A$51="2025年2月")/COUNTIFS(原始数据!$B$4:$B$51,原始数据!$B$4:$B$51&"",原始数据!$A$4:$A$51,原始数据!$A$4:$A$51&"")) -> 4 | H13: =IF(D13=0,"",F13/D13) -> 0.43207045 | I13: =IF(SUM(原始数据!$E$4:$E$51)=0,"",D13/SUM(原始数据!$E$4:$E$51)) -> 0.053425656
A14: =ROW()-2 -> 12 | B14: 2025年5月 | C14: =SUMIFS(原始数据!$C$4:$C$51,原始数据!$A$4:$A$51,"2025年5月") -> 509 | D14: =SUMIFS(原始数据!$E$4:$E$51,原始数据!$A$4:$A$51,"2025年5月") -> 957991 | E14: =SUMIFS(原始数据!$F$4:$F$51,原始数据!$A$4:$A$51,"2025年5月") -> 555350 | F14: =SUMIFS(原始数据!$G$4:$G$51,原始数据!$A$4:$A$51,"2025年5月") -> 402641 | G14: =SUMPRODUCT((原始数据!$A$4:$A$51="2025年5月")/COUNTIFS(原始数据!$B$4:$B$51,原始数据!$B$4:$B$51&"",原始数据!$A$4:$A$51,原始数据!$A$4:$A$51&"")) -> 4 | H14: =IF(D14=0,"",F14/D14) -> 0.42029727 | I14: =IF(SUM(原始数据!$E$4:$E$51)=0,"",D14/SUM(原始数据!$E$4:$E$51)) -> 0.041619947

Sheet 产品型号统计
A1: 产品型号维度统计分析
A2: 序号 | B2: 产品型号 | C2: 总销售数量 | D2: 总销售金额 | E2: 总成本 | F2: 总利润 | G2: 机型数 | H2: 利润率 | I2: 销售额占比
A3: =ROW()-2 -> 1 | B3: StarWatch Ultra | C3: =SUMIFS(原始数据!$C$4:$C$51,原始数据!$B$4:$B$51,"StarWatch Ultra") -> 3382 | D3: =SUMIFS(原始数据!$E$4:$E$51,原始数据!$B$4:$B$51,"StarWatch Ultra") -> 10142618 | E3: =SUMIFS(原始数据!$F$4:$F$51,原始数据!$B$4:$B$51,"StarWatch Ultra") -> 6087600 | F3: =SUMIFS(原始数据!$G$4:$G$51,原始数据!$B$4:$B$51,"StarWatch Ultra") -> 4055018 | G3: =SUMPRODUCT((原始数据!$B$4:$B$51="StarWatch Ultra")/COUNTIFS(原始数据!$B$4:$B$51,原始数据!$B$4:$B$51&"",原始数据!$B$4:$B$51,原始数据!$B$4:$B$51&"")) -> 1 | H3: =IF(D3=0,"",F3/D3) -> 0.39979993 | I3: =IF(SUM(原始数据!$E$4:$E$51)=0,"",D3/SUM(原始数据!$E$4:$E$51)) -> 0.44064634
A4: =ROW()-2 -> 2 | B4: StarWatch Pro | C4: =SUMIFS(原始数据!$C$4:$C$51,原始数据!$B$4:$B$51,"StarWatch Pro") -> 3532 | D4: =SUMIFS(原始数据!$E$4:$E$51,原始数据!$B$4:$B$51,"StarWatch Pro") -> 7060468 | E4: =SUMIFS(原始数据!$F$4:$F$51,原始数据!$B$4:$B$51,"StarWatch Pro") -> 3885200 | F4: =SUMIFS(原始数据!$G$4:$G$51,原始数据!$B$4:$B$51,"StarWatch Pro") -> 3175268 | G4: =SUMPRODUCT((原始数据!$B$4:$B$51="StarWatch Pro")/COUNTIFS(原始数据!$B$4:$B$51,原始数据!$B$4:$B$51&"",原始数据!$B$4:$B$51,原始数据!$B$4:$B$51&"")) -> 1 | H4: =IF(D4=0,"",F4/D4) -> 0.44972486 | I4: =IF(SUM(原始数据!$E$4:$E$51)=0,"",D4/SUM(原始数据!$E$4:$E$51)) -> 0.30674224
A5: =ROW()-2 -> 3 | B5: StarWatch SE | C5: =SUMIFS(原始数据!$C$4:$C$51,原始数据!$B$4:$B$51,"StarWatch SE") -> 3787 | D5: =SUMIFS(原始数据!$E$4:$E$51,原始数据!$B$4:$B$51,"StarWatch SE") -> 3783213 | E5: =SUMIFS(原始数据!$F$4:$F$51,原始数据!$B$4:$B$51,"StarWatch SE") -> 2082850 | F5: =SUMIFS(原始数据!$G$4:$G$51,原始数据!$B$4:$B$51,"StarWatch SE") -> 1700363 | G5: =SUMPRODUCT((原始数据!$B$4:$B$51="StarWatch SE")/COUNTIFS(原始数据!$B$4:$B$51,原始数据!$B$4:$B$51&"",原始数据!$B$4:$B$51,原始数据!$B$4:$B$51&"")) -> 1 | H5: =IF(D5=0,"",F5/D5) -> 0.44944945 | I5: =IF(SUM(原始数据!$E$4:$E$51)=0,"",D5/SUM(原始数据!$E$4:$E$51)) -> 0.1643618
A6: =ROW()-2 -> 4 | B6: StarWatch Lite | C6: =SUMIFS(原始数据!$C$4:$C$51,原始数据!$B$4:$B$51,"StarWatch Lite") -> 2906 | D6: =SUMIFS(原始数据!$E$4:$E$51,原始数据!$B$4:$B$51,"StarWatch Lite") -> 2031294 | E6: =SUMIFS(原始数据!$F$4:$F$51,原始数据!$B$4:$B$51,"StarWatch Lite") -> 1104280 | F6: =SUMIFS(原始数据!$G$4:$G$51,原始数据!$B$4:$B$51,"StarWatch Lite") -> 927014 | G6: =SUMPRODUCT((原始数据!$B$4:$B$51="StarWatch Lite")/COUNTIFS(原始数据!$B$4:$B$51,原始数据!$B$4:$B$51&"",原始数据!$B$4:$B$51,原始数据!$B$4:$B$51&"")) -> 1 | H6: =IF(D6=0,"",F6/D6) -> 0.45636624 | I6: =IF(SUM(原始数据!$E$4:$E$51)=0,"",D6/SUM(原始数据!$E$4:$E$51)) -> 0.088249627

Sheet 机型销售统计
A1: 机型销售统计
A2: 序号 | B2: 产品型号 | C2: 销售数量(只) | D2: 销售金额(元) | E2: 成本(元) | F2: 利润(元) | G2: 利润率 | H2: 销售额占比 | I2: 平均单价(元)
A3: =ROW()-2 -> 1 | B3: StarWatch Ultra | C3: =SUMIFS(原始数据!$C$4:$C$51,原始数据!$B$4:$B$51,$B3) -> 3382 | D3: =SUMIFS(原始数据!$E$4:$E$51,原始数据!$B$4:$B$51,$B3) -> 10142618 | E3: =SUMIFS(原始数据!$F$4:$F$51,原始数据!$B$4:$B$51,$B3) -> 6087600 | F3: =SUMIFS(原始数据!$G$4:$G$51,原始数据!$B$4:$B$51,$B3) -> 4055018 | G3: =IF(D3=0,"",F3/D3) -> 0.39979993 | H3: =IF(SUM(原始数据!$E$4:$E$51)=0,"",D3/SUM(原始数据!$E$4:$E$51)) -> 0.44064634 | I3: =IF(C3=0,"",D3/C3) -> 2999
A4: =ROW()-2 -> 2 | B4: StarWatch Pro | C4: =SUMIFS(原始数据!$C$4:$C$51,原始数据!$B$4:$B$51,$B4) -> 3532 | D4: =SUMIFS(原始数据!$E$4:$E$51,原始数据!$B$4:$B$51,$B4) -> 7060468 | E4: =SUMIFS(原始数据!$F$4:$F$51,原始数据!$B$4:$B$51,$B4) -> 3885200 | F4: =SUMIFS(原始数据!$G$4:$G$51,原始数据!$B$4:$B$51,$B4) -> 3175268 | G4: =IF(D4=0,"",F4/D4) -> 0.44972486 | H4: =IF(SUM(原始数据!$E$4:$E$51)=0,"",D4/SUM(原始数据!$E$4:$E$51)) -> 0.30674224 | I4: =IF(C4=0,"",D4/C4) -> 1999
A5: =ROW()-2 -> 3 | B5: StarWatch SE | C5: =SUMIFS(原始数据!$C$4:$C$51,原始数据!$B$4:$B$51,$B5) -> 3787 | D5: =SUMIFS(原始数据!$E$4:$E$51,原始数据!$B$4:$B$51,$B5) -> 3783213 | E5: =SUMIFS(原始数据!$F$4:$F$51,原始数据!$B$4:$B$51,$B5) -> 2082850 | F5: =SUMIFS(原始数据!$G$4:$G$51,原始数据!$B$4:$B$51,$B5) -> 1700363 | G5: =IF(D5=0,"",F5/D5) -> 0.44944945 | H5: =IF(SUM(原始数据!$E$4:$E$51)=0,"",D5/SUM(原始数据!$E$4:$E$51)) -> 0.1643618 | I5: =IF(C5=0,"",D5/C5) -> 999
A6: =ROW()-2 -> 4 | B6: StarWatch Lite | C6: =SUMIFS(原始数据!$C$4:$C$51,原始数据!$B$4:$B$51,$B6) -> 2906 | D6: =SUMIFS(原始数据!$E$4:$E$51,原始数据!$B$4:$B$51,$B6) -> 2031294 | E6: =SUMIFS(原始数据!$F$4:$F$51,原始数据!$B$4:$B$51,$B6) -> 1104280 | F6: =SUMIFS(原始数据!$G$4:$G$51,原始数据!$B$4:$B$51,$B6) -> 927014 | G6: =IF(D6=0,"",F6/D6) -> 0.45636624 | H6: =IF(SUM(原始数据!$E$4:$E$51)=0,"",D6/SUM(原始数据!$E$4:$E$51)) -> 0.088249627 | I6: =IF(C6=0,"",D6/C6) -> 699
B7: 合计 | C7: =SUM(原始数据!$C$4:$C$51) -> 13607 | D7: =SUM(原始数据!$E$4:$E$51) -> 23017593 | E7: =SUM(原始数据!$F$4:$F$51) -> 13159930 | F7: =SUM(原始数据!$G$4:$G$51) -> 9857663 | G7: =IF(D7=0,"",F7/D7) -> 0.42826646 | H7: =IF(SUM(原始数据!$E$4:$E$51)=0,"",D7/SUM(原始数据!$E$4:$E$51)) -> 1 | I7: =IF(C7=0,"",D7/C7) -> 1691.5994

Sheet 月份×机型交叉表
A1: 月份 × 机型 销售金额交叉表（元）
A2: 月份 | B2: StarWatch Ultra | C2: StarWatch Pro | D2: StarWatch SE | E2: StarWatch Lite | F2: 合计
A3: 2025年1月 | B3: =SUMIFS(原始数据!$E$4:$E$51,原始数据!$A$4:$A$51,$A3,原始数据!$B$4:$B$51,B$2) -> 1376541 | C3: =SUMIFS(原始数据!$E$4:$E$51,原始数据!$A$4:$A$51,$A3,原始数据!$B$4:$B$51,C$2) -> 813593 | D3: =SUMIFS(原始数据!$E$4:$E$51,原始数据!$A$4:$A$51,$A3,原始数据!$B$4:$B$51,D$2) -> 91908 | E3: =SUMIFS(原始数据!$E$4:$E$51,原始数据!$A$4:$A$51,$A3,原始数据!$B$4:$B$51,E$2) -> 95763 | F3: =SUMIFS(原始数据!$E$4:$E$51,原始数据!$A$4:$A$51,$A3) -> 2377805
A4: 2025年2月 | B4: =SUMIFS(原始数据!$E$4:$E$51,原始数据!$A$4:$A$51,$A4,原始数据!$B$4:$B$51,B$2) -> 452849 | C4: =SUMIFS(原始数据!$E$4:$E$51,原始数据!$A$4:$A$51,$A4,原始数据!$B$4:$B$51,C$2) -> 439780 | D4: =SUMIFS(原始数据!$E$4:$E$51,原始数据!$A$4:$A$51,$A4,原始数据!$B$4:$B$51,D$2) -> 193806 | E4: =SUMIFS(原始数据!$E$4:$E$51,原始数据!$A$4:$A$51,$A4,原始数据!$B$4:$B$51,E$2) -> 143295 | F4: =SUMIFS(原始数据!$E$4:$E$51,原始数据!$A$4:$A$51,$A4) -> 1229730
A5: 2025年3月 | B5: =SUMIFS(原始数据!$E$4:$E$51,原始数据!$A$4:$A$51,$A5,原始数据!$B$4:$B$51,B$2) -> 1376541 | C5: =SUMIFS(原始数据!$E$4:$E$51,原始数据!$A$4:$A$51,$A5,原始数据!$B$4:$B$51,C$2) -> 913543 | D5: =SUMIFS(原始数据!$E$4:$E$51,原始数据!$A$4:$A$51,$A5,原始数据!$B$4:$B$51,D$2) -> 425574 | E5: =SUMIFS(原始数据!$E$4:$E$51,原始数据!$A$4:$A$51,$A5,原始数据!$B$4:$B$51,E$2) -> 92268 | F5: =SUMIFS(原始数据!$E$4:$E$51,原始数据!$A$4:$A$51,$A5) -> 2807926
A6: 2025年4月 | B6: =SUMIFS(原始数据!$E$4:$E$51,原始数据!$A$4:$A$51,$A6,原始数据!$B$4:$B$51,B$2) -> 887704 | C6: =SUMIFS(原始数据!$E$4:$E$51,原始数据!$A$4:$A$51,$A6,原始数据!$B$4:$B$51,C$2) -> 717641 | D6: =SUMIFS(原始数据!$E$4:$E$51,原始数据!$A$4:$A$51,$A6,原始数据!$B$4:$B$51,D$2) -> 381618 | E6: =SUMIFS(原始数据!$E$4:$E$51,原始数据!$A$4:$A$51,$A6,原始数据!$B$4:$B$51,E$2) -> 86676 | F6: =SUMIFS(原始数据!$E$4:$E$51,原始数据!$A$4:$A$51,$A6) -> 2073639
A7: 2025年5月 | B7: =SUMIFS(原始数据!$E$4:$E$51,原始数据!$A$4:$A$51,$A7,原始数据!$B$4:$B$51,B$2) -> 572809 | C7: =SUMIFS(原始数据!$E$4:$E$51,原始数据!$A$4:$A$51,$A7,原始数据!$B$4:$B$51,C$2) -> 191904 | D7: =SUMIFS(原始数据!$E$4:$E$51,原始数据!$A$4:$A$51,$A7,原始数据!$B$4:$B$51,D$2) -> 126873 | E7: =SUMIFS(原始数据!$E$4:$E$51,原始数据!$A$4:$A$51,$A7,原始数据!$B$4:$B$51,E$2) -> 66405 | F7: =SUMIFS(原始数据!$E$4:$E$51,原始数据!$A$4:$A$51,$A7) -> 957991
A8: 2025年6月 | B8: =SUMIFS(原始数据!$E$4:$E$51,原始数据!$A$4:$A$51,$A8,原始数据!$B$4:$B$51,B$2) -> 278907 | C8: =SUMIFS(原始数据!$E$4:$E$51,原始数据!$A$4:$A$51,$A8,原始数据!$B$4:$B$51,C$2) -> 397801 | D8: =SUMIFS(原始数据!$E$4:$E$51,原始数据!$A$4:$A$51,$A8,原始数据!$B$4:$B$51,D$2) -> 387612 | E8: =SUMIFS(原始数据!$E$4:$E$51,原始数据!$A$4:$A$51,$A8,原始数据!$B$4:$B$51,E$2) -> 236262 | F8: =SUMIFS(原始数据!$E$4:$E$51,原始数据!$A$4:$A$51,$A8) -> 1300582
A9: 2025年7月 | B9: =SUMIFS(原始数据!$E$4:$E$51,原始数据!$A$4:$A$51,$A9,原始数据!$B$4:$B$51,B$2) -> 1235588 | C9: =SUMIFS(原始数据!$E$4:$E$51,原始数据!$A$4:$A$51,$A9,原始数据!$B$4:$B$51,C$2) -> 733633 | D9: =SUMIFS(原始数据!$E$4:$E$51,原始数据!$A$4:$A$51,$A9,原始数据!$B$4:$B$51,D$2) -> 445554 | E9: =SUMIFS(原始数据!$E$4:$E$51,原始数据!$A$4:$A$51,$A9,原始数据!$B$4:$B$51,E$2) -> 126519 | F9: =SUMIFS(原始数据!$E$4:$E$51,原始数据!$A$4:$A$51,$A9) -> 2541294
A10: 2025年8月 | B10: =SUMIFS(原始数据!$E$4:$E$51,原始数据!$A$4:$A$51,$A10,原始数据!$B$4:$B$51,B$2) -> 575808 | C10: =SUMIFS(原始数据!$E$4:$E$51,原始数据!$A$4:$A$51,$A10,原始数据!$B$4:$B$51,C$2) -> 877561 | D10: =SUMIFS(原始数据!$E$4:$E$51,原始数据!$A$4:$A$51,$A10,原始数据!$B$4:$B$51,D$2) -> 293706 | E10: =SUMIFS(原始数据!$E$4:$E$51,原始数据!$A$4:$A$51,$A10,原始数据!$B$4:$B$51,E$2) -> 250941 | F10: =SUMIFS(原始数据!$E$4:$E$51,原始数据!$A$4:$A$51,$A10) -> 1998016
A11: 2025年9月 | B11: =SUMIFS(原始数据!$E$4:$E$51,原始数据!$A$4:$A$51,$A11,原始数据!$B$4:$B$51,B$2) -> 1481506 | C11: =SUMIFS(原始数据!$E$4:$E$51,原始数据!$A$4:$A$51,$A11,原始数据!$B$4:$B$51,C$2) -> 617691 | D11: =SUMIFS(原始数据!$E$4:$E$51,原始数据!$A$4:$A$51,$A11,原始数据!$B$4:$B$51,D$2) -> 221778 | E11: =SUMIFS(原始数据!$E$4:$E$51,原始数据!$A$4:$A$51,$A11,原始数据!$B$4:$B$51,E$2) -> 266319 | F11: =SUMIFS(原始数据!$E$4:$E$51,原始数据!$A$4:$A$51,$A11) -> 2587294
A12: 2025年10月 | B12: =SUMIFS(原始数据!$E$4:$E$51,原始数据!$A$4:$A$51,$A12,原始数据!$B$4:$B$51,B$2) -> 482839 | C12: =SUMIFS(原始数据!$E$4:$E$51,原始数据!$A$4:$A$51,$A12,原始数据!$B$4:$B$51,C$2) -> 165917 | D12: =SUMIFS(原始数据!$E$4:$E$51,原始数据!$A$4:$A$51,$A12,原始数据!$B$4:$B$51,D$2) -> 491508 | E12: =SUMIFS(原始数据!$E$4:$E$51,原始数据!$A$4:$A$51,$A12,原始数据!$B$4:$B$51,E$2) -> 327132 | F12: =SUMIFS(原始数据!$E$4:$E$51,原始数据!$A$4:$A$51,$A12) -> 1467396
A13: 2025年11月 | B13: =SUMIFS(原始数据!$E$4:$E$51,原始数据!$A$4:$A$51,$A13,原始数据!$B$4:$B$51,B$2) -> 665778 | C13: =SUMIFS(原始数据!$E$4:$E$51,原始数据!$A$4:$A$51,$A13,原始数据!$B$4:$B$51,C$2) -> 873563 | D13: =SUMIFS(原始数据!$E$4:$E$51,原始数据!$A$4:$A$51,$A13,原始数据!$B$4:$B$51,D$2) -> 253746 | E13: =SUMIFS(原始数据!$E$4:$E$51,原始数据!$A$4:$A$51,$A13,原始数据!$B$4:$B$51,E$2) -> 206904 | F13: =SUMIFS(原始数据!$E$4:$E$51,原始数据!$A$4:$A$51,$A13) -> 1999991
A14: 2025年12月 | B14: =SUMIFS(原始数据!$E$4:$E$51,原始数据!$A$4:$A$51,$A14,原始数据!$B$4:$B$51,B$2) -> 755748 | C14: =SUMIFS(原始数据!$E$4:$E$51,原始数据!$A$4:$A$51,$A14,原始数据!$B$4:$B$51,C$2) -> 317841 | D14: =SUMIFS(原始数据!$E$4:$E$51,原始数据!$A$4:$A$51,$A14,原始数据!$B$4:$B$51,D$2) -> 469530 | E14: =SUMIFS(原始数据!$E$4:$E$51,原始数据!$A$4:$A$51,$A14,原始数据!$B$4:$B$51,E$2) -> 132810 | F14: =SUMIFS(原始数据!$E$4:$E$51,原始数据!$A$4:$A$51,$A14) -> 1675929
A15: 合计 | B15: =SUMIFS(原始数据!$E$4:$E$51,原始数据!$B$4:$B$51,B$2) -> 10142618 | C15: =SUMIFS(原始数据!$E$4:$E$51,原始数据!$B$4:$B$51,C$2) -> 7060468 | D15: =SUMIFS(原始数据!$E$4:$E$51,原始数据!$B$4:$B$51,D$2) -> 3783213 | E15: =SUMIFS(原始数据!$E$4:$E$51,原始数据!$B$4:$B$51,E$2) -> 2031294 | F15: =SUM(原始数据!$E$4:$E$51) -> 23017593
